{
    "posts": [
        { 
            "id": 1,
            "image":"../../../../assets/images/ba.jpg",
            "nom": "Burger a",
            "prix": 2340,
            "quantity":100,
            "description": "Science is an enterprise that should"
        },
        { 
            "id": 2,
            "image":"../../../../assets/images/bd.jpg",
            "nom": "Burger b",
            "prix": 2340,
            "quantity":100,
            "description": "Science is an enterprise that should"},
        { 
            "id": 3,
            "image":"../../../../assets/images/bd.jpg",
            "nom": "Burger a",
            "prix": 2340,
            "quantity":100,
            "description": "Science is an enterprise that should"
        },
        { 
            "id": 4,
            "image":"../../../../assets/images/ba.jpg",
            "nom": "Burger a",
            "prix": 2340,
            "quantity":100,
            "description": "Science is an enterprise that should"
        }
    ]
}